youtubemeta/__init__.py
youtubemeta/__main__.py
youtubemeta/useragents.py
youtubemeta/youtube.py
youtubemeta-0.0.2.dist-info/LICENSE
youtubemeta-0.0.2.dist-info/METADATA
youtubemeta-0.0.2.dist-info/WHEEL
youtubemeta-0.0.2.dist-info/top_level.txt
youtubemeta-0.0.2.dist-info/RECORD
