Metadata-Version: 2.1
Name: youtubemeta
Version: 0.0.2
Summary: Download YouTube channel data
Home-page: https://github.com/forgetso/youtubemeta
Author: Chris Taylor
License: UNKNOWN
Platform: UNKNOWN
Classifier: Programming Language :: Python :: 3
Classifier: License :: Public Domain
Classifier: Operating System :: OS Independent
Requires-Python: >=3.6
